Topsis_Ritik_101917101.py
Topsis_Ritik_101917101-0.0.1.dist-info/LICENSE
Topsis_Ritik_101917101-0.0.1.dist-info/METADATA
Topsis_Ritik_101917101-0.0.1.dist-info/WHEEL
Topsis_Ritik_101917101-0.0.1.dist-info/top_level.txt
Topsis_Ritik_101917101-0.0.1.dist-info/RECORD
